locksmith/__init__.py
locksmith/locksmith.py
locksmith-1.1.dist-info/LICENSE
locksmith-1.1.dist-info/METADATA
locksmith-1.1.dist-info/WHEEL
locksmith-1.1.dist-info/top_level.txt
locksmith-1.1.dist-info/RECORD
