Metadata-Version: 2.1
Name: locksmith
Version: 1.1
Summary: Your liaison between repository secrets and the great beyond.
Home-page: https://github.com/wcarhart/locksmith
Author: Will Carhart
Author-email: wcarhart@sandiego.edu
License: MIT
Platform: UNKNOWN
Classifier: Programming Language :: Python :: 3
Classifier: License :: OSI Approved :: MIT License
Classifier: Operating System :: OS Independent
